<annotation verified="yes">
	<folder>이동우_labeling</folder>
	<filename>20210918_142609.jpg</filename>
	<path>C:\Users\User\Documents\labeling\labeling\이동우_labeling\20210918_142609.jpg</path>
	<source>
		<database>Unknown</database>
	</source>
	<size>
		<width>3024</width>
		<height>4032</height>
		<depth>3</depth>
	</size>
	<segmented>0</segmented>
	<object>
		<name>apart_parking</name>
		<pose>Unspecified</pose>
		<truncated>0</truncated>
		<difficult>0</difficult>
		<bndbox>
			<xmin>2254</xmin>
			<ymin>1713</ymin>
			<xmax>2302</xmax>
			<ymax>1748</ymax>
		</bndbox>
	</object>
	<object>
		<name>disabled_parking</name>
		<pose>Unspecified</pose>
		<truncated>0</truncated>
		<difficult>0</difficult>
		<bndbox>
			<xmin>2199</xmin>
			<ymin>1643</ymin>
			<xmax>2289</xmax>
			<ymax>1707</ymax>
		</bndbox>
	</object>
</annotation>
