<annotation verified="yes">
	<folder>이동우_labeling</folder>
	<filename>20210918_144852.jpg</filename>
	<path>C:\Users\User\Documents\labeling\labeling\이동우_labeling\20210918_144852.jpg</path>
	<source>
		<database>Unknown</database>
	</source>
	<size>
		<width>3024</width>
		<height>4032</height>
		<depth>3</depth>
	</size>
	<segmented>0</segmented>
	<object>
		<name>disabled_parking</name>
		<pose>Unspecified</pose>
		<truncated>0</truncated>
		<difficult>0</difficult>
		<bndbox>
			<xmin>1781</xmin>
			<ymin>1410</ymin>
			<xmax>1885</xmax>
			<ymax>1461</ymax>
		</bndbox>
	</object>
	<object>
		<name>apart_parking</name>
		<pose>Unspecified</pose>
		<truncated>0</truncated>
		<difficult>0</difficult>
		<bndbox>
			<xmin>1925</xmin>
			<ymin>1417</ymin>
			<xmax>1981</xmax>
			<ymax>1450</ymax>
		</bndbox>
	</object>
</annotation>
